{
    "@context": {
        "@version": "1.1"
    },
    "id": "https://api.weather.gov/zones/fire/SDZ331",
    "type": "Feature",
    "geometry": {
        "type": "Polygon",
        "coordinates": [
            [
                [
                    -101.1544952,
                    44.6899108
                ],
                [
                    -101.15459439999999,
                    44.630012499999999
                ],
                [
                    -101.1548995,
                    44.602611500000002
                ],
                [
                    -101.1548004,
                    44.579212099999999
                ],
                [
                    -101.15459439999999,
                    44.574611599999997
                ],
                [
                    -101.1548995,
                    44.5239105
                ],
                [
                    -101.1548004,
                    44.516212400000001
                ],
                [
                    -101.1551971,
                    44.4918136
                ],
                [
                    -101.1551971,
                    44.343112900000001
                ],
                [
                    -101.1577987,
                    44.343112900000001
                ],
                [
                    -101.16679380000001,
                    44.342311800000004
                ],
                [
                    -101.166893,
                    44.334613800000007
                ],
                [
                    -101.16659540000001,
                    44.315212200000005
                ],
                [
                    -101.166893,
                    44.281513200000006
                ],
                [
                    -101.166893,
                    44.258510500000007
                ],
                [
                    -101.1666946,
                    44.248912800000006
                ],
                [
                    -101.166397,
                    44.204711900000007
                ],
                [
                    -101.166893,
                    44.185310300000005
                ],
                [
                    -101.16679380000001,
                    44.168312000000007
                ],
                [
                    -101.1481933,
                    44.168113700000006
                ],
                [
                    -101.1000976,
                    44.168312000000007
                ],
                [
                    -101.0940933,
                    44.168510400000009
                ],
                [
                    -101.08679959999999,
                    44.168312000000007
                ],
                [
                    -101.0739974,
                    44.168312000000007
                ],
                [
                    -101.0472946,
                    44.168510400000009
                ],
                [
                    -101.0468978,
                    44.161411200000011
                ],
                [
                    -101.04659269999999,
                    44.125011400000012
                ],
                [
                    -101.04660029999999,
                    44.008712700000011
                ],
                [
                    -101.04699699999999,
                    44.000011400000012
                ],
                [
                    -101.0467987,
                    43.995010300000011
                ],
                [
                    -101.06359859999999,
                    43.99491110000001
                ],
                [
                    -101.06419369999999,
                    43.986412000000009
                ],
                [
                    -101.0643997,
                    43.980510700000011
                ],
                [
                    -101.06419369999999,
                    43.956611600000009
                ],
                [
                    -101.06430049999999,
                    43.875011400000012
                ],
                [
                    -101.06399529999999,
                    43.854511200000012
                ],
                [
                    -101.07043349999999,
                    43.847373700000013
                ],
                [
                    -101.1425852,
                    43.83665100000001
                ],
                [
                    -101.14826170000001,
                    43.822197500000009
                ],
                [
                    -101.17092100000001,
                    43.82632490000001
                ],
                [
                    -101.1736755,
                    43.80588250000001
                ],
                [
                    -101.2129213,
                    43.807625900000012
                ],
                [
                    -101.2279968,
                    43.794410700000014
                ],
                [
                    -101.9237888,
                    43.879380500000018
                ],
                [
                    -102.0194623,
                    43.968972700000016
                ],
                [
                    -102.0190963,
                    43.990310600000015
                ],
                [
                    -102.0191955,
                    43.994510600000012
                ],
                [
                    -102.00729369999999,
                    43.994510600000012
                ],
                [
                    -102.00749959999999,
                    44.017711600000013
                ],
                [
                    -102.00739279999999,
                    44.030811300000011
                ],
                [
                    -102.0075988,
                    44.038013400000011
                ],
                [
                    -102.00729369999999,
                    44.063812200000008
                ],
                [
                    -102.00749959999999,
                    44.07221220000001
                ],
                [
                    -102.00740049999999,
                    44.089111300000013
                ],
                [
                    -102.00749959999999,
                    44.124011900000013
                ],
                [
                    -102.00769799999999,
                    44.139312700000012
                ],
                [
                    -102.00769799999999,
                    44.183113000000013
                ],
                [
                    -102.00749959999999,
                    44.201713500000011
                ],
                [
                    -102.00739279999999,
                    44.250110600000014
                ],
                [
                    -102.00749959999999,
                    44.315311400000013
                ],
                [
                    -102.00719449999998,
                    44.342613200000009
                ],
                [
                    -102.00099939999998,
                    44.344711300000007
                ],
                [
                    -102.00129689999999,
                    44.404010700000008
                ],
                [
                    -102.00099939999998,
                    44.415313700000006
                ],
                [
                    -102.00079339999998,
                    44.435012800000003
                ],
                [
                    -102.00119779999997,
                    44.500812500000002
                ],
                [
                    -102.00039669999997,
                    44.5172119
                ],
                [
                    -101.98938549999997,
                    44.5277496
                ],
                [
                    -101.94803309999998,
                    44.538980000000002
                ],
                [
                    -101.82890359999998,
                    44.536640900000002
                ],
                [
                    -101.81694009999998,
                    44.530056600000002
                ],
                [
                    -101.80371829999999,
                    44.5426146
                ],
                [
                    -101.78637609999998,
                    44.543694000000002
                ],
                [
                    -101.75701759999998,
                    44.559170100000003
                ],
                [
                    -101.74112579999998,
                    44.5744136
                ],
                [
                    -101.68899399999998,
                    44.579910400000003
                ],
                [
                    -101.67198829999998,
                    44.589649300000005
                ],
                [
                    -101.52940899999999,
                    44.577048900000008
                ],
                [
                    -101.50139399999999,
                    44.588851500000011
                ],
                [
                    -101.485266,
                    44.608619200000014
                ],
                [
                    -101.46338489999999,
                    44.610488300000014
                ],
                [
                    -101.4479209,
                    44.646243400000017
                ],
                [
                    -101.4242163,
                    44.64487380000002
                ],
                [
                    -101.4063713,
                    44.658217500000021
                ],
                [
                    -101.37097850000001,
                    44.660262000000017
                ],
                [
                    -101.3659894,
                    44.689375800000015
                ],
                [
                    -101.3375623,
                    44.693373500000014
                ],
                [
                    -101.3263697,
                    44.684023600000017
                ],
                [
                    -101.21060130000001,
                    44.703108000000014
                ],
                [
                    -101.13819880000001,
                    44.747013000000017
                ],
                [
                    -101.13719940000001,
                    44.742313300000013
                ],
                [
                    -101.13699340000001,
                    44.690013800000017
                ],
                [
                    -101.1544952,
                    44.6899108
                ]
            ]
        ]
    },
    "properties": {
        "@id": "https://api.weather.gov/zones/fire/SDZ331",
        "@type": "wx:Zone",
        "id": "SDZ331",
        "type": "fire",
        "name": "Haakon County Area",
        "effectiveDate": "2023-03-08T21:00:00+00:00",
        "expirationDate": "2200-01-01T00:00:00+00:00",
        "state": "SD",
        "cwa": [
            "UNR"
        ],
        "forecastOffices": [
            "https://api.weather.gov/offices/UNR"
        ],
        "timeZone": [
            "America/Chicago"
        ],
        "observationStations": [],
        "radarStation": null
    }
}